tetris_gymnasium/__init__.py
tetris_gymnasium/components/__init__.py
tetris_gymnasium/components/tetromino.py
tetris_gymnasium/components/tetromino_holder.py
tetris_gymnasium/components/tetromino_queue.py
tetris_gymnasium/components/tetromino_randomizer.py
tetris_gymnasium/envs/__init__.py
tetris_gymnasium/envs/tetris.py
tetris_gymnasium/envs/tetris_fn.py
tetris_gymnasium/functional/__init__.py
tetris_gymnasium/functional/core.py
tetris_gymnasium/functional/queue.py
tetris_gymnasium/functional/tetrominoes.py
tetris_gymnasium/mappings/__init__.py
tetris_gymnasium/mappings/actions.py
tetris_gymnasium/mappings/rewards.py
tetris_gymnasium/wrappers/__init__.py
tetris_gymnasium/wrappers/grouped.py
tetris_gymnasium/wrappers/observation.py
tetris_gymnasium-0.3.0.dist-info/LICENSE
tetris_gymnasium-0.3.0.dist-info/METADATA
tetris_gymnasium-0.3.0.dist-info/WHEEL
tetris_gymnasium-0.3.0.dist-info/RECORD
