Metadata-Version: 2.3
Name: tetris-gymnasium
Version: 0.3.0
Summary: A fully configurable Gymnasium compatible Tetris environment
Author: mw
Author-email: maximilian.weichart@icloud.com
Requires-Python: >=3.10,<4.0
Classifier: Programming Language :: Python :: 3
Classifier: Programming Language :: Python :: 3.10
Classifier: Programming Language :: Python :: 3.11
Classifier: Programming Language :: Python :: 3.12
Classifier: Programming Language :: Python :: 3.13
Requires-Dist: chex (>=0.1.87,<0.2.0)
Requires-Dist: gymnasium (>=0.28.1)
Requires-Dist: jax (>=0.4.34,<0.5.0)
Requires-Dist: numpy (>=1.21.6,<2.0.0)
Requires-Dist: opencv-python (>=4.10.0.84,<5.0.0.0)
